forgejo_releases_ics/__init__.py
forgejo_releases_ics/__main__.py
forgejo_releases_ics-0.1.0.dist-info/COPYING
forgejo_releases_ics-0.1.0.dist-info/METADATA
forgejo_releases_ics-0.1.0.dist-info/WHEEL
forgejo_releases_ics-0.1.0.dist-info/entry_points.txt
forgejo_releases_ics-0.1.0.dist-info/top_level.txt
forgejo_releases_ics-0.1.0.dist-info/RECORD
