Metadata-Version: 2.2
Name: forgejo-releases-ics
Version: 0.1.0
Summary: Get calendar of Forgejo releases
Author-email: Robert Wolff <mahlzahn@posteo.de>
License: GNU General Public License v3 or later (GPLv3+)
Project-URL: Source, https://codeberg.org/mahlzahn/forgejo-releases-ics
Project-URL: Issues, https://codeberg.org/mahlzahn/forgejo-releases-ics/issues
Classifier: Development Status :: 4 - Beta
Classifier: Environment :: Console
Classifier: Topic :: Utilities
Classifier: Operating System :: POSIX :: Linux
Classifier: Programming Language :: Python :: 3
Classifier: License :: OSI Approved :: GNU General Public License v3 or later (GPLv3+)
Requires-Python: >=3.8
License-File: COPYING
Requires-Dist: icalendar
Provides-Extra: full
Requires-Dist: argcomplete; extra == "full"
